ncdu_compare/__init__.py
ncdu_compare-0.0.8.dist-info/METADATA
ncdu_compare-0.0.8.dist-info/WHEEL
ncdu_compare-0.0.8.dist-info/entry_points.txt
ncdu_compare-0.0.8.dist-info/licenses/LICENSE
ncdu_compare-0.0.8.dist-info/RECORD
