Metadata-Version: 2.3
Name: ncdu_compare
Version: 0.0.8
Summary: Compare ncdu export files and show difference to find what took most space since previous measurement
Project-URL: Homepage, https://github.com/yaroslaff/ncdu-compare
Project-URL: Issues, https://github.com/yaroslaff/ncdu-compare/issues
Author-email: Yaroslav Polyakov <yaroslaff@gmail.com>
License-File: LICENSE
Classifier: License :: OSI Approved :: MIT License
Classifier: Operating System :: OS Independent
Classifier: Programming Language :: Python :: 3
Requires-Python: >=3.8
